janus_logging/__init__.py
janus_logging/version.py
janus_logging-1.3.2.dist-info/LICENSE
janus_logging-1.3.2.dist-info/METADATA
janus_logging-1.3.2.dist-info/WHEEL
janus_logging-1.3.2.dist-info/top_level.txt
janus_logging-1.3.2.dist-info/RECORD
