Metadata-Version: 2.1
Name: janus-logging
Version: 1.3.2
Summary: sync and async logging within one logger instance
Home-page: https://github.com/madkote/janus-logging
Author: madkote
Author-email: madkote <madkote@bluewin.ch>
License: MIT License
Download-URL: https://github.com/madkote/janus-logging/archive/1.3.2.tar.gz
Keywords: async,logging,log,json,asyncio,output
Platform: any
Classifier: Programming Language :: Python
Classifier: Programming Language :: Python :: 3
Classifier: Programming Language :: Python :: 3.6
Classifier: Programming Language :: Python :: 3.7
Classifier: Topic :: Utilities
Classifier: Topic :: Software Development :: Libraries
Classifier: Topic :: Software Development :: Libraries :: Python Modules
Classifier: Topic :: System :: Logging
Classifier: Framework :: AsyncIO
Classifier: Operating System :: OS Independent
Classifier: Intended Audience :: Developers
Requires-Python: >=3.6.0
Provides-Extra: dev
Requires-Dist: uvloop (==0.14.*) ; extra == 'dev'
Provides-Extra: test
Requires-Dist: uvloop (==0.14.*) ; extra == 'test'
Requires-Dist: bandit ; extra == 'test'
Requires-Dist: flake8 ; extra == 'test'
Requires-Dist: pytest ; extra == 'test'
Requires-Dist: pytest-cov ; extra == 'test'
Requires-Dist: tox ; extra == 'test'
